{
  "datetime": 1588854205,
  "donate_url": "",
  "error": false,
  "filehash": "dcfede21b4f2305555dd113284414a59",
  "filename": "EvolutionX_4.3_crownlte-10.0-20200507-1223-OFFICIAL.zip",
  "forum_url": "",
  "id": "4f1ebd0fd928dbcf5a6fed325555036970ad83899782612549aefb9229868501",
  "maintainer": "Robert Balmbra",
  "maintainer_url": "https://forum.xda-developers.com/member.php?u=4834466",
  "news_url": "https://t.me/EvolutionXOfficial",
  "size": 1283414096,
  "telegram_username": "robbalmbra",
  "url": "https://sourceforge.net/projects/evo9810ota/files/devices/crownlte/07-05-20/EvolutionX_4.3_crownlte-10.0-20200507-1223-OFFICIAL.zip/download",
  "version": "Ten",
  "website_url": "https://evolution-x.org"
}